spacyopentapioca/__init__.py
spacyopentapioca/entity_linker.py
tests/__init__.py
tests/test_opentapioca.py
spacyopentapioca-0.1.7.dist-info/LICENSE
spacyopentapioca-0.1.7.dist-info/METADATA
spacyopentapioca-0.1.7.dist-info/WHEEL
spacyopentapioca-0.1.7.dist-info/entry_points.txt
spacyopentapioca-0.1.7.dist-info/top_level.txt
spacyopentapioca-0.1.7.dist-info/RECORD
