Metadata-Version: 2.1
Name: spacyopentapioca
Version: 0.1.7
Summary: A spaCy wrapper of OpenTapioca for named entity linking on Wikidata
Home-page: https://github.com/UB-Mannheim/spacyopentapioca
Author: Renat Shigapov
License: MIT
Classifier: License :: OSI Approved :: MIT License
Classifier: Intended Audience :: Developers
Classifier: Intended Audience :: Education
Classifier: Intended Audience :: Science/Research
Classifier: Operating System :: OS Independent
Classifier: Programming Language :: Python
Classifier: Programming Language :: Python :: 3
Classifier: Programming Language :: Python :: 3.6
Classifier: Programming Language :: Python :: 3.7
Classifier: Programming Language :: Python :: 3.8
Classifier: Programming Language :: Python :: 3.9
Classifier: Topic :: Software Development :: Libraries
Classifier: Topic :: Software Development :: Libraries :: Python Modules
Requires-Python: >=3.6
License-File: LICENSE
Requires-Dist: spacy (>=3.1.4)
Requires-Dist: requests (>=2.24.0)
